onetimelink/__init__.py
onetimelink/admin.py
onetimelink/api.py
onetimelink/apps.py
onetimelink/models.py
onetimelink/presettings.py
onetimelink/test.py
onetimelink/urls.py
onetimelink/views.py
onetimelink/migrations/0001_initial.py
onetimelink/migrations/__init__.py
onetimelink/static/css/not_available.css
onetimelink/static/css/site.css
onetimelink/static/js/jquery-3.4.1.min.js
onetimelink/static/js/jquery-3.4.1.min.map
onetimelink/templates/not_avallible.html
onetimelink/templates/site.html
onetimelink/templates/sitedownload_changelist.html
django_onetimelink-2.0.dist-info/LICENSE
django_onetimelink-2.0.dist-info/METADATA
django_onetimelink-2.0.dist-info/WHEEL
django_onetimelink-2.0.dist-info/top_level.txt
django_onetimelink-2.0.dist-info/RECORD
