Metadata-Version: 2.1
Name: django-onetimelink
Version: 2.0
Summary: A django one-time file streaming application
Home-page: https://github.com/HiroshiFuu/django-onetimelink
Download-URL: https://pypi.python.org/pypi/django-onetimelink
Author: FENG Hao
Author-email: hiroshifuu@outlook.com
License: BSD
Keywords: django one-time file link serve
Classifier: Development Status :: 5 - Production/Stable
Classifier: Framework :: Django :: 2.0
Classifier: Framework :: Django :: 3.0
Classifier: License :: OSI Approved :: BSD License
Classifier: Operating System :: OS Independent
Classifier: Programming Language :: Python :: 3 :: Only
Classifier: Environment :: Console
Classifier: Natural Language :: English
Classifier: Intended Audience :: Developers
Classifier: Topic :: Internet
License-File: LICENSE
Requires-Dist: django
